LICENSE
README.md
setup.py
ci_sdr/__init__.py
ci_sdr.egg-info/PKG-INFO
ci_sdr.egg-info/SOURCES.txt
ci_sdr.egg-info/dependency_links.txt
ci_sdr.egg-info/requires.txt
ci_sdr.egg-info/top_level.txt
ci_sdr/np/__init__.py
ci_sdr/np/wiener_filter.py
ci_sdr/pt/__init__.py
ci_sdr/pt/sdr.py
ci_sdr/pt/toeplitz.py
ci_sdr/pt/wiener_filter.py