Metadata-Version: 2.1
Name: ci-sdr
Version: 0.0.0
Summary: A sample Python project
Home-page: https://github.com/fgnt/ci_sdr
Author: Christoph Boeddeker
License: UNKNOWN
Platform: UNKNOWN
Classifier: Development Status :: 3 - Alpha
Classifier: Intended Audience :: Developers
Classifier: Topic :: Software Development :: Build Tools
Classifier: License :: OSI Approved :: MIT License
Classifier: Programming Language :: Python :: 3
Classifier: Programming Language :: Python :: 3.6
Classifier: Programming Language :: Python :: 3.7
Classifier: Programming Language :: Python :: 3.8
Classifier: Programming Language :: Python :: 3.9
Classifier: Programming Language :: Python :: 3 :: Only
Requires-Python: >=3.6, <4
Provides-Extra: all
License-File: LICENSE
